LICENSE
MANIFEST.in
pyproject.toml
setup.py
costsensitive/__init__.py
costsensitive/vwrapper.pyx
costsensitive.egg-info/PKG-INFO
costsensitive.egg-info/SOURCES.txt
costsensitive.egg-info/dependency_links.txt
costsensitive.egg-info/requires.txt
costsensitive.egg-info/top_level.txt
src/calcv.c