Metadata-Version: 2.1
Name: costsensitive
Version: 0.1.2.13.post15
Summary: Reductions for Cost-Sensitive Multi-Class Classification
Home-page: https://github.com/david-cortes/costsensitive
Author: David Cortes
Keywords: cost sensitive multi class,cost-sensitive multi-class classification,weighted all pairs,filter tree
Requires-Python: >=3
License-File: LICENSE
Requires-Dist: numpy>=1.25
Requires-Dist: scipy
Requires-Dist: joblib>=0.13
Requires-Dist: cython
